fyn_runner/__init__.py
fyn_runner/config.py
fyn_runner/main.py
fyn_runner/job_management/__init__.py
fyn_runner/job_management/config.py
fyn_runner/job_management/job.py
fyn_runner/job_management/job_activity_tracking.py
fyn_runner/job_management/job_manager.py
fyn_runner/server/__init__.py
fyn_runner/server/config.py
fyn_runner/server/message.py
fyn_runner/server/server_proxy.py
fyn_runner/system/__init__.py
fyn_runner/system/collection.py
fyn_runner/utilities/__init__.py
fyn_runner/utilities/config.py
fyn_runner/utilities/config_manager.py
fyn_runner/utilities/file_manager.py
fyn_runner/utilities/logging_utilities.py
fyn_runner-0.0.5.dist-info/licenses/LICENSE.md
fyn_runner-0.0.5.dist-info/METADATA
fyn_runner-0.0.5.dist-info/WHEEL
fyn_runner-0.0.5.dist-info/top_level.txt
fyn_runner-0.0.5.dist-info/RECORD
