Metadata-Version: 2.4
Name: fyn-runner
Version: 0.0.5
Author: Fynbos Technologies
License-File: LICENSE.md
Requires-Dist: appdirs
Requires-Dist: fyn-api-client
Requires-Dist: nvidia-ml-py
Requires-Dist: psutil
Requires-Dist: py-cpuinfo
Requires-Dist: pydantic>=2.0
Requires-Dist: pyyaml
Requires-Dist: requests
Requires-Dist: websocket-client
Provides-Extra: dev
Requires-Dist: autopep8; extra == "dev"
Requires-Dist: flake8; extra == "dev"
Requires-Dist: pylint; extra == "dev"
Requires-Dist: pylint-pydantic; extra == "dev"
Requires-Dist: pre-commit; extra == "dev"
Dynamic: license-file
